<launch4jConfig>
  <dontWrapJar>false</dontWrapJar>
  <headerType>0</headerType>
  <jar>C:\projects\java\hl7inspector.trunk\dist\hl7inspector.jar</jar>
  <outfile>C:\projects\java\hl7inspector.trunk\dist\hl7inspector.exe</outfile>
  <errTitle></errTitle>
  <jarArgs></jarArgs>
  <chdir></chdir>
  <customProcName>true</customProcName>
  <stayAlive>false</stayAlive>
  <icon>C:\projects\java\hl7inspector.trunk\application.ico</icon>
  <jre>
    <path></path>
    <minVersion>1.6.0</minVersion>
    <maxVersion></maxVersion>
    <initialHeapSize>0</initialHeapSize>
    <maxHeapSize>256</maxHeapSize>
    <args>-Djava.net.useSystemProxies=true</args>
  </jre>
  <versionInfo>
    <fileVersion>2.2.0.0</fileVersion>
    <txtFileVersion>2.2</txtFileVersion>
    <fileDescription>Hl7 Inspector 2</fileDescription>
    <copyright>elomagic</copyright>
    <productVersion>2.2.0.0</productVersion>
    <txtProductVersion>2.2</txtProductVersion>
    <productName>Hl7 Inspector 2.2</productName>
    <companyName>elomagic.de</companyName>
    <internalName>hl7inspector</internalName>
    <originalFilename>hl7inspector.exe</originalFilename>
  </versionInfo>
</launch4jConfig>